lib/neopixel.py
lib/ring.py
lib/sonos.py
micropython_audio_remote-0.0.1.dist-info/LICENSE
micropython_audio_remote-0.0.1.dist-info/METADATA
micropython_audio_remote-0.0.1.dist-info/WHEEL
micropython_audio_remote-0.0.1.dist-info/top_level.txt
micropython_audio_remote-0.0.1.dist-info/RECORD
